{
  "_class": "group",
  "do_objectID": "DF234D34-98D3-41B8-B282-F598A30E0E2E",
  "exportOptions": {
    "_class": "exportOptions",
    "do_objectID": "396B4F11-6F72-422A-9B26-A2AFFAAD7696",
    "exportFormats": [
    ],
    "includedLayerIds": [
    ],
    "layerOptions": 0,
    "shouldTrim": false
  },
  "frame": {
    "_class": "rect",
    "constrainProportions": false,
    "do_objectID": "8B8B6772-6B79-47DB-B451-6DDD71F2540E",
    "height": 723,
    "width": 1440,
    "x": 0,
    "y": 80
  },
  "hasClickThrough": false,
  "isFlippedHorizontal": false,
  "isFlippedVertical": false,
  "isLocked": false,
  "isVisible": true,
  "layerListExpandedType": 0,
  "layers": [
    {
      "class": "symbolInstance",
      "id": "4DEEC27C-7955-4640-93BC-5BA0CB1508E6"
    },
    {
      "class": "symbolInstance",
      "id": "26C51EC1-C5DE-4B9A-9639-B08A5E5EFBF4"
    },
    {
      "class": "symbolInstance",
      "id": "0DCCC066-84C5-430E-A34F-56D99040A8A4"
    },
    {
      "class": "symbolInstance",
      "id": "373BD845-C9B1-4093-B3ED-B32BF9301981"
    },
    {
      "class": "symbolInstance",
      "id": "845BA478-E94B-48CA-B4FE-CEEF80AE4E5B"
    }
  ],
  "name": "ends in ends out chart and parameter",
  "nameIsFixed": true,
  "resizingConstraint": 63,
  "resizingType": 0,
  "rotation": 0,
  "shouldBreakMaskChain": false,
  "style": {
    "_class": "style",
    "do_objectID": "AE8547B8-11E0-4CEA-9AE0-F5B59EC79DCF",
    "endDecorationType": 0,
    "miterLimit": 10,
    "startDecorationType": 0
  }
}