{
  "_class": "shapeGroup",
  "clippingMaskMode": 0,
  "do_objectID": "414A452F-69A3-46B5-9F29-F969D48A4EA0",
  "exportOptions": {
    "_class": "exportOptions",
    "exportFormats": [
    ],
    "includedLayerIds": [
    ],
    "layerOptions": 0,
    "shouldTrim": false
  },
  "frame": {
    "_class": "rect",
    "constrainProportions": false,
    "height": 45,
    "width": 7,
    "x": 70,
    "y": 42
  },
  "hasClickThrough": false,
  "hasClippingMask": false,
  "isFlippedHorizontal": false,
  "isFlippedVertical": false,
  "isLocked": false,
  "isVisible": true,
  "layerListExpandedType": 0,
  "layers": [
    {
      "class": "rectangle",
      "id": "7317DACE-4B7C-417E-AE2B-ADCED6FD1241"
    }
  ],
  "name": "bar_fall",
  "nameIsFixed": false,
  "resizingConstraint": 63,
  "resizingType": 0,
  "rotation": 0,
  "shouldBreakMaskChain": false,
  "style": {
    "sharedObjectID": "AE11F4F3-8E75-47D6-BBCE-36D6377049AA"
  },
  "windingRule": 1
}