{
  "_class": "shapeGroup",
  "clippingMaskMode": 0,
  "do_objectID": "1CE3BC3B-3F42-4D80-A8E3-D80675285CCF",
  "exportOptions": {
    "_class": "exportOptions",
    "exportFormats": [
    ],
    "includedLayerIds": [
    ],
    "layerOptions": 0,
    "shouldTrim": false
  },
  "frame": {
    "_class": "rect",
    "constrainProportions": false,
    "height": 49,
    "width": 7,
    "x": 620,
    "y": 288
  },
  "hasClickThrough": false,
  "hasClippingMask": false,
  "isFlippedHorizontal": false,
  "isFlippedVertical": false,
  "isLocked": false,
  "isVisible": true,
  "layerListExpandedType": 0,
  "layers": [
    {
      "class": "rectangle",
      "id": "87F6F24F-8F3C-4F91-83A8-59FA41690C48"
    }
  ],
  "name": "bar_fall",
  "nameIsFixed": false,
  "resizingConstraint": 63,
  "resizingType": 0,
  "rotation": 0,
  "shouldBreakMaskChain": false,
  "style": {
    "sharedObjectID": "AE11F4F3-8E75-47D6-BBCE-36D6377049AA"
  },
  "windingRule": 1
}