{
  "_class": "group",
  "do_objectID": "7C1CB2CC-98BA-40AF-99DC-D8A429125C88",
  "exportOptions": {
    "_class": "exportOptions",
    "exportFormats": [
    ],
    "includedLayerIds": [
    ],
    "layerOptions": 0,
    "shouldTrim": false
  },
  "frame": {
    "_class": "rect",
    "constrainProportions": false,
    "height": 154,
    "width": 324,
    "x": 0,
    "y": 0
  },
  "hasClickThrough": false,
  "isFlippedHorizontal": false,
  "isFlippedVertical": false,
  "isLocked": false,
  "isVisible": true,
  "layerListExpandedType": 0,
  "layers": [
    {
      "class": "shapeGroup",
      "id": "4F187CE7-D705-48FE-ABAB-CC39F2DE4FB8"
    },
    {
      "class": "symbolInstance",
      "id": "4794BB1D-F3FE-4CEA-A915-E40B69E2C504"
    },
    {
      "class": "group",
      "id": "F1A13D8D-7F3A-4E22-B01B-6DF42B2F7852"
    },
    {
      "class": "group",
      "id": "0F8CCBC5-8000-4E5D-B53F-B521D8D60938"
    },
    {
      "class": "text",
      "id": "E6A66064-DC5A-474C-84D3-E0906E28B272"
    },
    {
      "class": "text",
      "id": "4144DE27-FA14-4EEF-8A88-7D1EEDC3DE84"
    }
  ],
  "name": "Trade Duration",
  "nameIsFixed": true,
  "resizingConstraint": 63,
  "resizingType": 0,
  "rotation": 0,
  "shouldBreakMaskChain": false,
  "style": {
    "_class": "style",
    "endDecorationType": 0,
    "miterLimit": 10,
    "startDecorationType": 0
  }
}