{
  "_class": "group",
  "do_objectID": "B20ACA3F-C5C2-44D1-9620-24D79BFAF2D2",
  "exportOptions": {
    "_class": "exportOptions",
    "do_objectID": "26B6ECCB-E596-47FB-BB07-D97DA179D7F0",
    "exportFormats": [
    ],
    "includedLayerIds": [
    ],
    "layerOptions": 0,
    "shouldTrim": false
  },
  "frame": {
    "_class": "rect",
    "constrainProportions": false,
    "do_objectID": "8DD720A1-1A27-4D80-8BCC-F29A98FB0125",
    "height": 31.06666666666666,
    "width": 1440,
    "x": 0,
    "y": 95.27111111111111
  },
  "hasClickThrough": false,
  "isFlippedHorizontal": false,
  "isFlippedVertical": false,
  "isLocked": false,
  "isVisible": true,
  "layerListExpandedType": 2,
  "layers": [
    {
      "class": "shapeGroup",
      "id": "BD78D682-9482-4A60-810C-4D9D720715E7"
    },
    {
      "class": "group",
      "id": "881F8C8B-5ADF-4F6F-A13A-59012B38E197"
    }
  ],
  "name": "High barrier",
  "nameIsFixed": true,
  "resizingConstraint": 63,
  "resizingType": 0,
  "rotation": 0,
  "shouldBreakMaskChain": false,
  "style": {
    "_class": "style",
    "do_objectID": "933D31B8-E469-40E6-BCFA-0AD4FF8076AB",
    "endDecorationType": 0,
    "miterLimit": 10,
    "startDecorationType": 0
  }
}