{
  "_class": "symbolInstance",
  "do_objectID": "FF4EBB18-1689-4C75-B631-178DE2D6DAAB",
  "exportOptions": {
    "_class": "exportOptions",
    "exportFormats": [
    ],
    "includedLayerIds": [
    ],
    "layerOptions": 0,
    "shouldTrim": false
  },
  "frame": {
    "_class": "rect",
    "constrainProportions": false,
    "height": 40,
    "width": 200,
    "x": 16,
    "y": 16
  },
  "horizontalSpacing": 0,
  "isFlippedHorizontal": false,
  "isFlippedVertical": false,
  "isLocked": false,
  "isVisible": true,
  "layerListExpandedType": 0,
  "name": "Search",
  "nameIsFixed": true,
  "originalObjectID": "2A033881-99E2-4EA2-A09C-A571B3EE2D27",
  "overrideValues": [
    {
      "_class": "overrideValue",
      "overrideName": "61E7FA8D-CE88-4116-B503-268F047478D7_stringValue",
      "value": "\"AUD/JPY\" or \"Apple\""
    }
  ],
  "overrides": {
    "61E7FA8D-CE88-4116-B503-268F047478D7": "\"AUD/JPY\" or \"Apple\""
  },
  "resizingConstraint": 18,
  "resizingType": 0,
  "rotation": 0,
  "scale": 1,
  "shouldBreakMaskChain": false,
  "style": {
    "_class": "style",
    "endDecorationType": 0,
    "miterLimit": 10,
    "startDecorationType": 0
  },
  "symbolID": "84B0C472-BB5A-4D8E-862F-DE29FA02DCAD",
  "verticalSpacing": 0
}