{
  "_class": "group",
  "do_objectID": "3CC26FC6-7568-480E-88E1-ACF65D132952",
  "exportOptions": {
    "_class": "exportOptions",
    "exportFormats": [
    ],
    "includedLayerIds": [
    ],
    "layerOptions": 0,
    "shouldTrim": false
  },
  "frame": {
    "_class": "rect",
    "constrainProportions": false,
    "height": 32,
    "width": 32,
    "x": 216,
    "y": 0
  },
  "hasClickThrough": false,
  "isFlippedHorizontal": false,
  "isFlippedVertical": false,
  "isLocked": false,
  "isVisible": true,
  "layerListExpandedType": 0,
  "layers": [
    {
      "class": "shapeGroup",
      "id": "F2B37E13-F791-4705-818E-76DFD114FBC8"
    },
    {
      "class": "symbolInstance",
      "id": "7874862E-3173-460A-9B68-1D5B263C8174"
    }
  ],
  "name": "btn-copy",
  "nameIsFixed": true,
  "resizingConstraint": 63,
  "resizingType": 0,
  "rotation": 0,
  "shouldBreakMaskChain": false,
  "style": {
    "_class": "style",
    "endDecorationType": 0,
    "miterLimit": 10,
    "startDecorationType": 0
  },
  "userInfo": {
    "com.invision.prototype": {
      "backgroundOpacity": 0,
      "closeOnClickOutside": 1,
      "componentType": "SRLink",
      "fixOverlayPosition": 1,
      "gesture": 1,
      "linkType": 0,
      "maintainScrollPositionAfterGesture": 0,
      "maintainScrollPositionAfterRedirect": 0,
      "openURLInNewWindow": 0,
      "overlayPosition": 0,
      "overlayTransition": 0,
      "redirectAfter": 0,
      "reverseTransitionOnClose": 1,
      "scrollToPosition": 0,
      "smoothScrolling": 0,
      "stayOnTargetScreen": 0,
      "targetArtboardID": "64B418E2-36CA-435A-BFCE-00F0B279175C",
      "transition": 0
    }
  }
}