{
  "_class": "group",
  "do_objectID": "2ADC20F3-9D4E-4CB8-9809-F69224A838BC",
  "exportOptions": {
    "_class": "exportOptions",
    "exportFormats": [
    ],
    "includedLayerIds": [
    ],
    "layerOptions": 0,
    "shouldTrim": false
  },
  "frame": {
    "_class": "rect",
    "constrainProportions": false,
    "height": 528,
    "width": 232,
    "x": 0,
    "y": 0
  },
  "hasClickThrough": false,
  "isFlippedHorizontal": false,
  "isFlippedVertical": false,
  "isLocked": false,
  "isVisible": true,
  "layerListExpandedType": 0,
  "layers": [
    {
      "class": "shapeGroup",
      "id": "F1F04312-208B-4DD4-9E5D-FB8D5104F6A7"
    },
    {
      "class": "symbolInstance",
      "id": "88DAC304-6282-45F4-83FA-E7B32633302D"
    },
    {
      "class": "symbolInstance",
      "id": "ABD4D380-DC12-4FFB-9B14-AA80632B0D67"
    },
    {
      "class": "symbolInstance",
      "id": "5FFE3D0C-CD97-4F41-BE80-0C2018ED581E"
    },
    {
      "class": "symbolInstance",
      "id": "B2D21359-F3A7-4041-A951-37E8A6026CB4"
    },
    {
      "class": "symbolInstance",
      "id": "9BF4F455-5288-42E7-B209-9436442FBC3F"
    },
    {
      "class": "symbolInstance",
      "id": "F7576A91-0BFB-4B18-BEF1-01B65260BCDB"
    },
    {
      "class": "symbolInstance",
      "id": "7B990316-276B-46D5-ABDC-BD00AC9ADC0C"
    },
    {
      "class": "symbolInstance",
      "id": "49AA429B-E227-4EF5-A9D6-967ACB678919"
    },
    {
      "class": "symbolInstance",
      "id": "283B0AB2-61BB-4D55-BC83-2035F55F184C"
    },
    {
      "class": "symbolInstance",
      "id": "9934C47E-55FA-4A21-8CB4-1069438D17CA"
    }
  ],
  "name": "Left Column",
  "nameIsFixed": true,
  "resizingConstraint": 63,
  "resizingType": 0,
  "rotation": 0,
  "shouldBreakMaskChain": false,
  "style": {
    "_class": "style",
    "endDecorationType": 0,
    "miterLimit": 10,
    "startDecorationType": 0
  }
}