{
  "_class": "group",
  "do_objectID": "E6F93BFC-535B-429A-AD2B-973975F2D272",
  "exportOptions": {
    "_class": "exportOptions",
    "exportFormats": [
    ],
    "includedLayerIds": [
    ],
    "layerOptions": 0,
    "shouldTrim": false
  },
  "frame": {
    "_class": "rect",
    "constrainProportions": false,
    "height": 16,
    "width": 16,
    "x": 0,
    "y": 0
  },
  "hasClickThrough": false,
  "isFlippedHorizontal": true,
  "isFlippedVertical": true,
  "isLocked": false,
  "isVisible": false,
  "layerListExpandedType": 0,
  "layers": [
    {
      "class": "shapeGroup",
      "id": "A39DA035-1BAB-4B01-BBA5-E7DBBB57A6DA"
    },
    {
      "class": "shapeGroup",
      "id": "F467D1C7-9730-4BA9-AB83-90CA9C6D6D98"
    },
    {
      "class": "shapeGroup",
      "id": "D52CFF78-C568-4DE6-AC0F-D7B17ED66A61"
    }
  ],
  "name": "Group",
  "nameIsFixed": false,
  "resizingConstraint": 63,
  "resizingType": 0,
  "rotation": 0,
  "shouldBreakMaskChain": false,
  "style": {
    "_class": "style",
    "endDecorationType": 0,
    "miterLimit": 10,
    "startDecorationType": 0
  }
}