{
  "_class": "group",
  "do_objectID": "0CFD2E4E-2F04-46DF-AC7E-4A04BD5AF4DE",
  "exportOptions": {
    "_class": "exportOptions",
    "do_objectID": "A9AC8299-63FD-4219-9904-B2A883A8FF0C",
    "exportFormats": [
    ],
    "includedLayerIds": [
    ],
    "layerOptions": 0,
    "shouldTrim": false
  },
  "frame": {
    "_class": "rect",
    "constrainProportions": false,
    "do_objectID": "4860A7E1-E299-49CC-AAA5-CA11B1230E98",
    "height": 528,
    "width": 632,
    "x": 16,
    "y": 152
  },
  "hasClickThrough": false,
  "isFlippedHorizontal": false,
  "isFlippedVertical": false,
  "isLocked": false,
  "isVisible": true,
  "layerListExpandedType": 2,
  "layers": [
    {
      "class": "shapeGroup",
      "id": "9523E0E2-4A0F-4389-AF15-3BE1924553EE"
    },
    {
      "class": "group",
      "id": "4AD6DB39-680B-4D23-B19F-8F9A0E4ECB37"
    },
    {
      "class": "group",
      "id": "48BD3247-DB65-41C4-800E-693BBA2BF64A"
    },
    {
      "class": "group",
      "id": "DD52E49A-5BCB-414E-9FE7-19EEBBE842BE"
    }
  ],
  "name": "List",
  "nameIsFixed": true,
  "resizingConstraint": 63,
  "resizingType": 0,
  "rotation": 0,
  "shouldBreakMaskChain": false,
  "style": {
    "_class": "style",
    "do_objectID": "44CFFB47-5C16-4653-9438-669B710909EF",
    "endDecorationType": 0,
    "miterLimit": 10,
    "shadows": [
      {
        "_class": "shadow",
        "blurRadius": 8,
        "color": {
          "_class": "color",
          "alpha": 0.14,
          "blue": 0.3215686274509804,
          "green": 0.188235294117647,
          "red": 0.1647058823529412
        },
        "contextSettings": {
          "_class": "graphicsContextSettings",
          "blendMode": 0,
          "opacity": 1
        },
        "isEnabled": true,
        "offsetX": 0,
        "offsetY": 2,
        "spread": 0
      }
    ],
    "startDecorationType": 0
  }
}