{
  "_class": "symbolInstance",
  "do_objectID": "830FDD91-1BED-4746-905E-ED6FDA7C48CC",
  "exportOptions": {
    "_class": "exportOptions",
    "do_objectID": "CF61C2BE-1A4E-4AE0-BF56-85C42661635A",
    "exportFormats": [
    ],
    "includedLayerIds": [
    ],
    "layerOptions": 0,
    "shouldTrim": false
  },
  "frame": {
    "_class": "rect",
    "constrainProportions": false,
    "do_objectID": "D4B00F6A-D574-44CC-8CD0-51FF685E13E9",
    "height": 32,
    "width": 168,
    "x": 16,
    "y": 40
  },
  "horizontalSpacing": 0,
  "isFlippedHorizontal": false,
  "isFlippedVertical": false,
  "isLocked": false,
  "isVisible": true,
  "layerListExpandedType": 0,
  "name": "list-9",
  "nameIsFixed": true,
  "originalObjectID": "3A1CD1C7-D976-49C5-8A1D-F4932B2465D0",
  "overrideValues": [
    {
      "_class": "overrideValue",
      "overrideName": "2A2BBEE9-55E0-4F80-9205-16D748D353FC_stringValue",
      "value": "Line"
    }
  ],
  "overrides": {
    "2A2BBEE9-55E0-4F80-9205-16D748D353FC": "Line"
  },
  "resizingConstraint": 63,
  "resizingType": 0,
  "rotation": 0,
  "scale": 1,
  "shouldBreakMaskChain": false,
  "style": {
    "_class": "style",
    "do_objectID": "A86EA741-DD2D-4FDD-9C9E-6EC79CF58F94",
    "endDecorationType": 0,
    "miterLimit": 10,
    "startDecorationType": 0
  },
  "symbolID": "8D15087E-24A7-4331-BA4D-9113A2EBBA24",
  "userInfo": {
  },
  "verticalSpacing": 0
}